<annotation>
	<folder>temp</folder>
	<filename>Screenshot_3.png</filename>
	<path>C:\Users\Admin\Desktop\TFMCreator\temp\Screenshot_3.png</path>
	<source>
		<database>Unknown</database>
	</source>
	<size>
		<width>1917</width>
		<height>1032</height>
		<depth>3</depth>
	</size>
	<segmented>0</segmented>
	<object>
		<name>CAPTCHA</name>
		<pose>Unspecified</pose>
		<truncated>0</truncated>
		<difficult>0</difficult>
		<bndbox>
			<xmin>708</xmin>
			<ymin>645</ymin>
			<xmax>790</xmax>
			<ymax>679</ymax>
		</bndbox>
	</object>
	<object>
		<name>F</name>
		<pose>Unspecified</pose>
		<truncated>0</truncated>
		<difficult>0</difficult>
		<bndbox>
			<xmin>710</xmin>
			<ymin>652</ymin>
			<xmax>731</xmax>
			<ymax>673</ymax>
		</bndbox>
	</object>
	<object>
		<name>Y</name>
		<pose>Unspecified</pose>
		<truncated>0</truncated>
		<difficult>0</difficult>
		<bndbox>
			<xmin>732</xmin>
			<ymin>650</ymin>
			<xmax>752</xmax>
			<ymax>676</ymax>
		</bndbox>
	</object>
	<object>
		<name>R</name>
		<pose>Unspecified</pose>
		<truncated>0</truncated>
		<difficult>0</difficult>
		<bndbox>
			<xmin>752</xmin>
			<ymin>653</ymin>
			<xmax>771</xmax>
			<ymax>677</ymax>
		</bndbox>
	</object>
	<object>
		<name>C</name>
		<pose>Unspecified</pose>
		<truncated>0</truncated>
		<difficult>0</difficult>
		<bndbox>
			<xmin>768</xmin>
			<ymin>648</ymin>
			<xmax>788</xmax>
			<ymax>676</ymax>
		</bndbox>
	</object>
</annotation>
